setup.py
status_tool/__init__.py
status_tool/status_tool.py
status_tool.egg-info/PKG-INFO
status_tool.egg-info/SOURCES.txt
status_tool.egg-info/dependency_links.txt
status_tool.egg-info/top_level.txt