Metadata-Version: 2.1
Name: status-tool
Version: 0.2
Summary: 用于离床判断
Home-page: https://github.com/yourname/my_package
Author: hy
Author-email: yue.huang@slaaplekker.cn
License: UNKNOWN
Platform: UNKNOWN
